unified_api_pkg/Octopus.py
unified_api_pkg/OctopusUtils.py
unified_api_pkg/__init__.py
unified_api_pkg/generalUtils.py
unified_api_pkg/logUtils.py
unified_api_pkg/project_dict_and_list.py
unified_api_pkg/qrcode.py
unified_api_pkg/terminal.py
unified_api_pkg/terminalUtils.py
unified_api_pkg/unifiedAPI.py
unified_api_pkg-0.79.2.dist-info/METADATA
unified_api_pkg-0.79.2.dist-info/WHEEL
unified_api_pkg-0.79.2.dist-info/top_level.txt
unified_api_pkg-0.79.2.dist-info/RECORD
