Metadata-Version: 2.1
Name: unified-api-pkg
Version: 0.79.2
Summary: Partial Application
Home-page: UNKNOWN
Author: EFTSolutions Stanley Yan
Author-email: stanleyyan@eftsolutions.com
License: UNKNOWN
Platform: UNKNOWN
Classifier: Programming Language :: Python :: 3
Classifier: License :: OSI Approved :: MIT License
Classifier: Operating System :: OS Independent
